pyagena/__init__.py
pyagena/_version.py
pyagena/cloud.py
pyagena/dataset.py
pyagena/localapi.py
pyagena/logger.py
pyagena/model.py
pyagena/network.py
pyagena/node.py
tests/__init__.py
tests/credentials.py
tests/template_load_asia.py
tests/template_load_cars.py
tests/test_2obs.py
tests/test_activation.py
tests/test_batch.py
tests/test_create_asia.py
tests/test_create_car_costs.py
tests/test_create_river_flooding.py
tests/test_dataset_getters.py
tests/test_load_and_calculate_cloud.py
tests/test_load_and_calculate_local.py
tests/test_load_and_sensitivity_cloud.py
tests/test_load_and_sensitivity_local.py
tests/test_local_activation.py
tests/test_local_setup.py
tests/test_model_settings.py
tests/test_non_string_ids.py
pyagena-1.0.4.dist-info/LICENSE
pyagena-1.0.4.dist-info/METADATA
pyagena-1.0.4.dist-info/WHEEL
pyagena-1.0.4.dist-info/top_level.txt
pyagena-1.0.4.dist-info/RECORD
