Metadata-Version: 2.1
Name: pyagena
Version: 1.0.4
Summary: Python utility library for agena.ai to create Bayesian network models from scratch or import existing models and export to agena.ai cloud or local API for calculations.
Home-page: https://github.com/AgenaRisk/api-py
Author: Erhan Pisirir, Eugene Dementiev
Author-email: support@agenarisk.com
License: UNKNOWN
Download-URL: https://github.com/AgenaRisk/api-py/archive/refs/tags/1.0.3.tar.gz
Platform: UNKNOWN
Classifier: Programming Language :: Python :: 3
Classifier: License :: OSI Approved :: MIT License
Classifier: Operating System :: OS Independent
Requires-Dist: matplotlib
Requires-Dist: networkx
Requires-Dist: pandas
Requires-Dist: requests
